Metadata-Version: 2.1
Name: newsmoris
Version: 0.1.0
Summary: Package to get news from various news site in Mauritius
Home-page: https://github.com/Abdur-RahmaanJ/newsmoris
Author: Abdur-Rahmaan Janhangeer
Author-email: arj.python@gmail.com
License: UNKNOWN
Project-URL: Bug Reports, https://github.com/Abdur-RahmaanJ/newsmoris/issues
Project-URL: Source, https://github.com/Abdur-RahmaanJ/newsmoris/
Keywords: mauritius news
Platform: UNKNOWN
Classifier: Development Status :: 3 - Alpha
Classifier: Intended Audience :: Developers
Classifier: License :: OSI Approved :: MIT License
Classifier: Programming Language :: Python :: 3.4
Classifier: Programming Language :: Python :: 3.5
Classifier: Programming Language :: Python :: 3.6
Classifier: Programming Language :: Python :: 3.7
Classifier: Programming Language :: Python :: 3.8
Classifier: Programming Language :: Python :: 3.9
Requires-Python: >=3.4
License-File: LICENSE
